README.rst
setup.py
aimlbotkernel/__init__.py
aimlbotkernel/__main__.py
aimlbotkernel/aimlbot.py
aimlbotkernel/install.py
aimlbotkernel/kernel.py
aimlbotkernel/setlogging.py
aimlbotkernel/utils.py
aimlbotkernel.egg-info/PKG-INFO
aimlbotkernel.egg-info/SOURCES.txt
aimlbotkernel.egg-info/dependency_links.txt
aimlbotkernel.egg-info/entry_points.txt
aimlbotkernel.egg-info/requires.txt
aimlbotkernel.egg-info/top_level.txt
aimlbotkernel/resources/aimlbotkernel.css
aimlbotkernel/resources/logo-32x32.png
aimlbotkernel/resources/logo-64x64.png