Metadata-Version: 1.1
Name: aimlbotkernel
Version: 1.0.4
Summary: A Chatbot kernel for Jupyter based on pyAIML
Home-page: https://github.com/paulovn/aiml-chatbot-kernel
Author: Paulo Villegas
Author-email: paulo.vllgs@gmail.com
License: 3-clause BSD license
Download-URL: https://github.com/paulovn/aiml-chatbot-kernel/tarball/v1.0.4
Keywords: AIML,chatbot,IPython,Jupyter,kernel
Platform: UNKNOWN
Classifier: Framework :: IPython
Classifier: Framework :: Jupyter
Classifier: Programming Language :: Python :: 2 :: Only
Classifier: Programming Language :: Python :: 2.7
Classifier: License :: OSI Approved :: BSD License
Classifier: Development Status :: 4 - Beta
Classifier: Topic :: Scientific/Engineering :: Artificial Intelligence
